Workbook

Sheet Lisez-moi
A1: Tableur de rentabilité – Phase 1 (Google Shopping, France)
A2: Créé le 12/10/2026. Toutes les cellules calculées sont des formules : change une entrée, tout se recalcule.
A4: CODE COULEUR
A5: Texte bleu = valeur saisie (hypothèse ou donnée relevée). Texte noir = formule. Texte vert = lien vers un autre onglet.
A6: Fond jaune = cellule que TU dois remplir ou vérifier (données Keyword Planner, prix fournisseurs).
A8: ORDRE CONSEILLÉ
A9: 1. Onglet « Paramètres » : vérifie TVA, frais Shopify, budget, CPC plafond (chaque valeur a sa source en colonne C).
A10: 2. Onglet « Mots-clés » : recopie depuis le Planificateur de mots-clés le volume et les enchères basse/haute de chaque mot-clé.
A11: 3. Onglet « Rentabilité » : saisis le coût produit et la livraison (HT) relevés chez le fournisseur. Le verdict se met à jour.
A12: 4. Onglet « Scénarios » : marge par vente et CPC moyen → résultat du mois à 1 %, 1,5 % et 2,5 % de conversion.
A14: CE QUI EST RÉEL / CE QUI EST HYPOTHÈSE
A15: Réel (relevé le 12/10/2026, source dans l'onglet « Sources ») : prix concurrents Zooplus, CPC médian Shopping Europe (Smec), règles douane UE.
... A19: Ceci n'est pas un avis fiscal : le taux de TVA (21 % BE ou 20 % FR / OSS) est à valider avec ton comptable.

Sheet Paramètres
A1: Paramètres (modifie les valeurs bleues)
A3: Paramètre | B3: Valeur | C3: Source / statut
A4: Taux de TVA appliqué au prix de vente | B4: 0.21 | C4: Donné par toi : TVA belge 21 % sous 10 000 €/an de ventes UE à distance ; sinon 20 % FR via OSS. À VALIDER avec ton comptable.
A5: Frais Shopify Payments (% du prix TTC) | B5: 0.015 | C5: Donné par toi ; cohérent avec getkanal.com (page tarifs Shopify FR relevée le 07/10/2026). Cartes Amex/hors UE : 2,7 %.
A6: Frais Shopify Payments fixes (€ / transaction) | B6: 0.25 | C6: Idem ligne 5.
A7: Budget publicitaire mensuel (€) | B7: 200 | C7: Donné par toi.
A8: CPC plafond de départ (€) | B8: 0.65 | C8: Donné par toi (0,60–0,70 €). Pour info : CPC médian Shopping Europe = 0,36 € (smarter-ecommerce.com, page mise à jour le 12/10/2026, toutes catégories).
A9: Seuil d'élimination : enchère haute moyenne (€) | B9: 1.2 | C9: Donné par toi.
A10: Marge brute cible – haute (€ / vente) | B10: 40 | C10: Donné par toi (35–40 €).
A11: Marge brute cible – basse (€ / vente) | B11: 35 | C11: Donné par toi.
A12: Droit de douane forfaitaire hors UE (€ / catégorie d'article) | B12: 3 | C12: En vigueur depuis le 01/07/2026, colis ≤ 150 €, jusqu'au 01/07/2028 (info.gouv.fr). Ne s'applique PAS si expédié depuis l'UE.
A13: Redevance UE de gestion hors UE (€ / article) | B13: 2 | C13: Prévue au 01/11/2026 ; montant de 2 € cité par plusieurs sources mais NON confirmé officiellement au 12/10/2026. Hors UE uniquement.
A14: Provision retours / litiges (% du CA TTC) | B14: 0.05 | C14: ESTIMATION (aucune donnée réelle). À ajuster après les premières ventes.
A15: Abonnement Shopify Basic (€ / mois) | B15: 36 | C15: speed-ecom.eu (tarifs vérifiés le 26/08/2026). À confirmer sur shopify.com/fr/tarifs.
... A17: Nombre moyen de jours par mois | B17: 30.4 | C17: Convention.
A18: Budget publicitaire par jour (€) | B18: =B7/B17 -> 6.5789474 | C18: Calcul.
A19: Clics par mois au CPC plafond | B19: =B7/B8 -> 307.69231 | C19: Calcul : budget ÷ CPC plafond (au CPC réel, souvent plus bas, tu auras plus de clics).

Sheet Mots-clés
A1: Mots-clés à tester dans le Planificateur (France, français, 12 derniers mois)
A2: Les mots-clés sont des PROPOSITIONS. Les colonnes jaunes sont vides : recopie les chiffres du Planificateur (ne pas inventer).
A4: Candidat | B4: Mot-clé | C4: Volume mensuel moyen | D4: Enchère basse haut de page (€) | E4: Enchère haute haut de page (€) | F4: Concurrence (Faible/Moyenne/Élevée) | G4: Statut vs seuil | H4: Note
A5: Lit orthopédique chien L/XL | B5: lit orthopédique chien | G5: =IF(E5="","à relever",IF(E5>Paramètres!$B$9,"AU-DESSUS du seuil","OK")) -> à relever
A6: Lit orthopédique chien L/XL | B6: lit orthopédique grand chien | G6: =IF(E6="","à relever",IF(E6>Paramètres!$B$9,"AU-DESSUS du seuil","OK")) -> à relever
A7: Lit orthopédique chien L/XL | B7: panier orthopédique chien | G7: =IF(E7="","à relever",IF(E7>Paramètres!$B$9,"AU-DESSUS du seuil","OK")) -> à relever
A8: Lit orthopédique chien L/XL | B8: lit mémoire de forme chien | G8: =IF(E8="","à relever",IF(E8>Paramètres!$B$9,"AU-DESSUS du seuil","OK")) -> à relever
A9: Lit orthopédique chien L/XL | B9: matelas orthopédique chien | G9: =IF(E9="","à relever",IF(E9>Paramètres!$B$9,"AU-DESSUS du seuil","OK")) -> à relever
A10: Lit orthopédique chien L/XL | B10: lit chien xl | G10: =IF(E10="","à relever",IF(E10>Paramètres!$B$9,"AU-DESSUS du seuil","OK")) -> à relever
A11: Lit orthopédique chien L/XL | B11: panier chien xxl | G11: =IF(E11="","à relever",IF(E11>Paramètres!$B$9,"AU-DESSUS du seuil","OK")) -> à relever
A12: Lit orthopédique chien L/XL | B12: lit pour chien âgé | G12: =IF(E12="","à relever",IF(E12>Paramètres!$B$9,"AU-DESSUS du seuil","OK")) -> à relever
A13: Lit orthopédique chien L/XL | B13: lit chien arthrose | G13: =IF(E13="","à relever",IF(E13>Paramètres!$B$9,"AU-DESSUS du seuil","OK")) -> à relever
A14: Lit orthopédique chien L/XL | B14: coussin orthopédique chien | G14: =IF(E14="","à relever",IF(E14>Paramètres!$B$9,"AU-DESSUS du seuil","OK")) -> à relever
A15: Lit orthopédique chien L/XL | B15: lit chien grande taille | G15: =IF(E15="","à relever",IF(E15>Paramètres!$B$9,"AU-DESSUS du seuil","OK")) -> à relever
A16: Lit orthopédique chien L/XL | B16: panier grand chien | G16: =IF(E16="","à relever",IF(E16>Paramètres!$B$9,"AU-DESSUS du seuil","OK")) -> à relever
... A95: Chariot de courses premium | B95: chariot courses senior | G95: =IF(E95="","à relever",IF(E95>Paramètres!$B$9,"AU-DESSUS du seuil","OK")) -> à relever
A97: Note : le Planificateur affiche des fourchettes (ex. « 1 k – 10 k ») tant que le compte n'a jamais dépensé. Saisis alors le milieu de fourchette et écris « fourchette » en colonne Note.

Sheet Rentabilité
A1: Rentabilité par candidat (1 vente = 1 article)
A2: Colonnes B–F : entrées. Colonnes G–H : tirées de l'onglet Mots-clés. Le reste : formules. Coûts fournisseurs en HT si tu récupères la TVA, sinon en TTC (voir comptable).
A4: Candidat | B4: Prix de vente TTC (€) | C4: Coût produit (€) | D4: Livraison au client (€) | E4: Expédié hors UE ? (OUI/NON) | F4: Nb catégories d'articles / colis | G4: Enchère haute moyenne (€) | H4: Volume mensuel cumulé | I4: Prix HT (€) | J4: Frais Shopify (€) | K4: Douane + redevance (€) | L4: Marge brute / vente (€) | M4: Achat max produit+livraison pour 40 € de marge | N4: Achat max pour 35 € de marge | O4: CPA maximal (€) | P4: Ventes/mois pour couvrir 200 € | Q4: Taux de conversion d'équilibre | R4: Marge après provision retours (€) | S4: Verdict
A5: Lit orthopédique chien L/XL | B5: 99 | E5: NON | F5: 1 | G5: =IF(COUNTIFS('Mots-clés'!$A$5:$A$95,A5,'Mots-clés'!$E$5:$E$95,">0")=0,"",AVERAGEIFS('Mots-clés'!$E$5:$E$95,'Mots-clés'!$A$5:$A$95,A5,'Mots-clés'!$E$5:$E$95,">0")) | H5: =IF(COUNTIFS('Mots-clés'!$A$5:$A$95,A5,'Mots-clés'!$C$5:$C$95,">0")=0,"",SUMIFS('Mots-clés'!$C$5:$C$95,'Mots-clés'!$A$5:$A$95,A5)) | I5: =B5/(1+Paramètres!$B$4) -> 81.818182 | J5: =B5*Paramètres!$B$5+Paramètres!$B$6 -> 1.735 | K5: =IF(E5="OUI",F5*Paramètres!$B$12+Paramètres!$B$13,0) -> 0 | L5: =IF(OR(C5="",D5=""),"à renseigner",I5-C5-D5-J5-K5) -> à renseigner | M5: =I5-J5-K5-Paramètres!$B$10 -> 40.083182 | N5: =I5-J5-K5-Paramètres!$B$11 -> 45.083182 | O5: =L5 -> à renseigner | P5: =IF(ISNUMBER(L5),IF(L5>0,Paramètres!$B$7/L5,"marge ≤ 0"),"") | Q5: =IF(ISNUMBER(L5),IF(L5>0,Paramètres!$B$8/L5,"marge ≤ 0"),"") | R5: =IF(ISNUMBER(L5),L5-B5*Paramètres!$B$14,"") | S5: =IF(G5="","Enchères à relever",IF(G5>Paramètres!$B$9,"ÉLIMINÉ : enchère > seuil",IF(NOT(ISNUMBER(L5)),"Coûts fournisseur à relever",IF(L5>=Paramètres!$B$10,"OK marge ≥ 40 €",IF(L5>=Paramètres!$B$11,"Limite : marge 35–40 €","ÉLIMINÉ : marge < 35 €"))))) -> Enchères à relever
A6: Couverture lestée adulte | B6: 89 | E6: NON | F6: 1 | G6: =IF(COUNTIFS('Mots-clés'!$A$5:$A$95,A6,'Mots-clés'!$E$5:$E$95,">0")=0,"",AVERAGEIFS('Mots-clés'!$E$5:$E$95,'Mots-clés'!$A$5:$A$95,A6,'Mots-clés'!$E$5:$E$95,">0")) | H6: =IF(COUNTIFS('Mots-clés'!$A$5:$A$95,A6,'Mots-clés'!$C$5:$C$95,">0")=0,"",SUMIFS('Mots-clés'!$C$5:$C$95,'Mots-clés'!$A$5:$A$95,A6)) | I6: =B6/(1+Paramètres!$B$4) -> 73.553719 | J6: =B6*Paramètres!$B$5+Paramètres!$B$6 -> 1.585 | K6: =IF(E6="OUI",F6*Paramètres!$B$12+Paramètres!$B$13,0) -> 0 | L6: =IF(OR(C6="",D6=""),"à renseigner",I6-C6-D6-J6-K6) -> à renseigner | M6: =I6-J6-K6-Paramètres!$B$10 -> 31.968719 | N6: =I6-J6-K6-Paramètres!$B$11 -> 36.968719 | O6: =L6 -> à renseigner | P6: =IF(ISNUMBER(L6),IF(L6>0,Paramètres!$B$7/L6,"marge ≤ 0"),"") | Q6: =IF(ISNUMBER(L6),IF(L6>0,Paramètres!$B$8/L6,"marge ≤ 0"),"") | R6: =IF(ISNUMBER(L6),L6-B6*Paramètres!$B$14,"") | S6: =IF(G6="","Enchères à relever",IF(G6>Paramètres!$B$9,"ÉLIMINÉ : enchère > seuil",IF(NOT(ISNUMBER(L6)),"Coûts fournisseur à relever",IF(L6>=Paramètres!$B$10,"OK marge ≥ 40 €",IF(L6>=Paramètres!$B$11,"Limite : marge 35–40 €","ÉLIMINÉ : marge < 35 €"))))) -> Enchères à relever
A7: Rampe / escalier chien | B7: 79 | E7: NON | F7: 1 | G7: =IF(COUNTIFS('Mots-clés'!$A$5:$A$95,A7,'Mots-clés'!$E$5:$E$95,">0")=0,"",AVERAGEIFS('Mots-clés'!$E$5:$E$95,'Mots-clés'!$A$5:$A$95,A7,'Mots-clés'!$E$5:$E$95,">0")) | H7: =IF(COUNTIFS('Mots-clés'!$A$5:$A$95,A7,'Mots-clés'!$C$5:$C$95,">0")=0,"",SUMIFS('Mots-clés'!$C$5:$C$95,'Mots-clés'!$A$5:$A$95,A7)) | I7: =B7/(1+Paramètres!$B$4) -> 65.289256 | J7: =B7*Paramètres!$B$5+Paramètres!$B$6 -> 1.435 | K7: =IF(E7="OUI",F7*Paramètres!$B$12+Paramètres!$B$13,0) -> 0 | L7: =IF(OR(C7="",D7=""),"à renseigner",I7-C7-D7-J7-K7) -> à renseigner | M7: =I7-J7-K7-Paramètres!$B$10 -> 23.854256 | N7: =I7-J7-K7-Paramètres!$B$11 -> 28.854256 | O7: =L7 -> à renseigner | P7: =IF(ISNUMBER(L7),IF(L7>0,Paramètres!$B$7/L7,"marge ≤ 0"),"") | Q7: =IF(ISNUMBER(L7),IF(L7>0,Paramètres!$B$8/L7,"marge ≤ 0"),"") | R7: =IF(ISNUMBER(L7),L7-B7*Paramètres!$B$14,"") | S7: =IF(G7="","Enchères à relever",IF(G7>Paramètres!$B$9,"ÉLIMINÉ : enchère > seuil",IF(NOT(ISNUMBER(L7)),"Coûts fournisseur à relever",IF(L7>=Paramètres!$B$10,"OK marge ≥ 40 €",IF(L7>=Paramètres!$B$11,"Limite : marge 35–40 €","ÉLIMINÉ : marge < 35 €"))))) -> Enchères à relever
A8: Réhausseur bureau assis-debout manuel | B8: 119 | E8: NON | F8: 1 | G8: =IF(COUNTIFS('Mots-clés'!$A$5:$A$95,A8,'Mots-clés'!$E$5:$E$95,">0")=0,"",AVERAGEIFS('Mots-clés'!$E$5:$E$95,'Mots-clés'!$A$5:$A$95,A8,'Mots-clés'!$E$5:$E$95,">0")) | H8: =IF(COUNTIFS('Mots-clés'!$A$5:$A$95,A8,'Mots-clés'!$C$5:$C$95,">0")=0,"",SUMIFS('Mots-clés'!$C$5:$C$95,'Mots-clés'!$A$5:$A$95,A8)) | I8: =B8/(1+Paramètres!$B$4) -> 98.347107 | J8: =B8*Paramètres!$B$5+Paramètres!$B$6 -> 2.035 | K8: =IF(E8="OUI",F8*Paramètres!$B$12+Paramètres!$B$13,0) -> 0 | L8: =IF(OR(C8="",D8=""),"à renseigner",I8-C8-D8-J8-K8) -> à renseigner | M8: =I8-J8-K8-Paramètres!$B$10 -> 56.312107 | N8: =I8-J8-K8-Paramètres!$B$11 -> 61.312107 | O8: =L8 -> à renseigner | P8: =IF(ISNUMBER(L8),IF(L8>0,Paramètres!$B$7/L8,"marge ≤ 0"),"") | Q8: =IF(ISNUMBER(L8),IF(L8>0,Paramètres!$B$8/L8,"marge ≤ 0"),"") | R8: =IF(ISNUMBER(L8),L8-B8*Paramètres!$B$14,"") | S8: =IF(G8="","Enchères à relever",IF(G8>Paramètres!$B$9,"ÉLIMINÉ : enchère > seuil",IF(NOT(ISNUMBER(L8)),"Coûts fournisseur à relever",IF(L8>=Paramètres!$B$10,"OK marge ≥ 40 €",IF(L8>=Paramètres!$B$11,"Limite : marge 35–40 €","ÉLIMINÉ : marge < 35 €"))))) -> Enchères à relever
A9: Arbre à chat XXL | B9: 119 | E9: NON | F9: 1 | G9: =IF(COUNTIFS('Mots-clés'!$A$5:$A$95,A9,'Mots-clés'!$E$5:$E$95,">0")=0,"",AVERAGEIFS('Mots-clés'!$E$5:$E$95,'Mots-clés'!$A$5:$A$95,A9,'Mots-clés'!$E$5:$E$95,">0")) | H9: =IF(COUNTIFS('Mots-clés'!$A$5:$A$95,A9,'Mots-clés'!$C$5:$C$95,">0")=0,"",SUMIFS('Mots-clés'!$C$5:$C$95,'Mots-clés'!$A$5:$A$95,A9)) | I9: =B9/(1+Paramètres!$B$4) -> 98.347107 | J9: =B9*Paramètres!$B$5+Paramètres!$B$6 -> 2.035 | K9: =IF(E9="OUI",F9*Paramètres!$B$12+Paramètres!$B$13,0) -> 0 | L9: =IF(OR(C9="",D9=""),"à renseigner",I9-C9-D9-J9-K9) -> à renseigner | M9: =I9-J9-K9-Paramètres!$B$10 -> 56.312107 | N9: =I9-J9-K9-Paramètres!$B$11 -> 61.312107 | O9: =L9 -> à renseigner | P9: =IF(ISNUMBER(L9),IF(L9>0,Paramètres!$B$7/L9,"marge ≤ 0"),"") | Q9: =IF(ISNUMBER(L9),IF(L9>0,Paramètres!$B$8/L9,"marge ≤ 0"),"") | R9: =IF(ISNUMBER(L9),L9-B9*Paramètres!$B$14,"") | S9: =IF(G9="","Enchères à relever",IF(G9>Paramètres!$B$9,"ÉLIMINÉ : enchère > seuil",IF(NOT(ISNUMBER(L9)),"Coûts fournisseur à relever",IF(L9>=Paramètres!$B$10,"OK marge ≥ 40 €",IF(L9>=Paramètres!$B$11,"Limite : marge 35–40 €","ÉLIMINÉ : marge < 35 €"))))) -> Enchères à relever
A10: Banc de musculation pliable | B10: 99 | E10: NON | F10: 1 | G10: =IF(COUNTIFS('Mots-clés'!$A$5:$A$95,A10,'Mots-clés'!$E$5:$E$95,">0")=0,"",AVERAGEIFS('Mots-clés'!$E$5:$E$95,'Mots-clés'!$A$5:$A$95,A10,'Mots-clés'!$E$5:$E$95,">0")) | H10: =IF(COUNTIFS('Mots-clés'!$A$5:$A$95,A10,'Mots-clés'!$C$5:$C$95,">0")=0,"",SUMIFS('Mots-clés'!$C$5:$C$95,'Mots-clés'!$A$5:$A$95,A10)) | I10: =B10/(1+Paramètres!$B$4) -> 81.818182 | J10: =B10*Paramètres!$B$5+Paramètres!$B$6 -> 1.735 | K10: =IF(E10="OUI",F10*Paramètres!$B$12+Paramètres!$B$13,0) -> 0 | L10: =IF(OR(C10="",D10=""),"à renseigner",I10-C10-D10-J10-K10) -> à renseigner | M10: =I10-J10-K10-Paramètres!$B$10 -> 40.083182 | N10: =I10-J10-K10-Paramètres!$B$11 -> 45.083182 | O10: =L10 -> à renseigner | P10: =IF(ISNUMBER(L10),IF(L10>0,Paramètres!$B$7/L10,"marge ≤ 0"),"") | Q10: =IF(ISNUMBER(L10),IF(L10>0,Paramètres!$B$8/L10,"marge ≤ 0"),"") | R10: =IF(ISNUMBER(L10),L10-B10*Paramètres!$B$14,"") | S10: =IF(G10="","Enchères à relever",IF(G10>Paramètres!$B$9,"ÉLIMINÉ : enchère > seuil",IF(NOT(ISNUMBER(L10)),"Coûts fournisseur à relever",IF(L10>=Paramètres!$B$10,"OK marge ≥ 40 €",IF(L10>=Paramètres!$B$11,"Limite : marge 35–40 €","ÉLIMINÉ : marge < 35 €"))))) -> Enchères à relever
A11: Haltères réglables | B11: 119 | E11: NON | F11: 1 | G11: =IF(COUNTIFS('Mots-clés'!$A$5:$A$95,A11,'Mots-clés'!$E$5:$E$95,">0")=0,"",AVERAGEIFS('Mots-clés'!$E$5:$E$95,'Mots-clés'!$A$5:$A$95,A11,'Mots-clés'!$E$5:$E$95,">0")) | H11: =IF(COUNTIFS('Mots-clés'!$A$5:$A$95,A11,'Mots-clés'!$C$5:$C$95,">0")=0,"",SUMIFS('Mots-clés'!$C$5:$C$95,'Mots-clés'!$A$5:$A$95,A11)) | I11: =B11/(1+Paramètres!$B$4) -> 98.347107 | J11: =B11*Paramètres!$B$5+Paramètres!$B$6 -> 2.035 | K11: =IF(E11="OUI",F11*Paramètres!$B$12+Paramètres!$B$13,0) -> 0 | L11: =IF(OR(C11="",D11=""),"à renseigner",I11-C11-D11-J11-K11) -> à renseigner | M11: =I11-J11-K11-Paramètres!$B$10 -> 56.312107 | N11: =I11-J11-K11-Paramètres!$B$11 -> 61.312107 | O11: =L11 -> à renseigner | P11: =IF(ISNUMBER(L11),IF(L11>0,Paramètres!$B$7/L11,"marge ≤ 0"),"") | Q11: =IF(ISNUMBER(L11),IF(L11>0,Paramètres!$B$8/L11,"marge ≤ 0"),"") | R11: =IF(ISNUMBER(L11),L11-B11*Paramètres!$B$14,"") | S11: =IF(G11="","Enchères à relever",IF(G11>Paramètres!$B$9,"ÉLIMINÉ : enchère > seuil",IF(NOT(ISNUMBER(L11)),"Coûts fournisseur à relever",IF(L11>=Paramètres!$B$10,"OK marge ≥ 40 €",IF(L11>=Paramètres!$B$11,"Limite : marge 35–40 €","ÉLIMINÉ : marge < 35 €"))))) -> Enchères à relever
A12: Chariot de courses premium | B12: 79 | E12: NON | F12: 1 | G12: =IF(COUNTIFS('Mots-clés'!$A$5:$A$95,A12,'Mots-clés'!$E$5:$E$95,">0")=0,"",AVERAGEIFS('Mots-clés'!$E$5:$E$95,'Mots-clés'!$A$5:$A$95,A12,'Mots-clés'!$E$5:$E$95,">0")) | H12: =IF(COUNTIFS('Mots-clés'!$A$5:$A$95,A12,'Mots-clés'!$C$5:$C$95,">0")=0,"",SUMIFS('Mots-clés'!$C$5:$C$95,'Mots-clés'!$A$5:$A$95,A12)) | I12: =B12/(1+Paramètres!$B$4) -> 65.289256 | J12: =B12*Paramètres!$B$5+Paramètres!$B$6 -> 1.435 | K12: =IF(E12="OUI",F12*Paramètres!$B$12+Paramètres!$B$13,0) -> 0 | L12: =IF(OR(C12="",D12=""),"à renseigner",I12-C12-D12-J12-K12) -> à renseigner | M12: =I12-J12-K12-Paramètres!$B$10 -> 23.854256 | N12: =I12-J12-K12-Paramètres!$B$11 -> 28.854256 | O12: =L12 -> à renseigner | P12: =IF(ISNUMBER(L12),IF(L12>0,Paramètres!$B$7/L12,"marge ≤ 0"),"") | Q12: =IF(ISNUMBER(L12),IF(L12>0,Paramètres!$B$8/L12,"marge ≤ 0"),"") | R12: =IF(ISNUMBER(L12),L12-B12*Paramètres!$B$14,"") | S12: =IF(G12="","Enchères à relever",IF(G12>Paramètres!$B$9,"ÉLIMINÉ : enchère > seuil",IF(NOT(ISNUMBER(L12)),"Coûts fournisseur à relever",IF(L12>=Paramètres!$B$10,"OK marge ≥ 40 €",IF(L12>=Paramètres!$B$11,"Limite : marge 35–40 €","ÉLIMINÉ : marge < 35 €"))))) -> Enchères à relever
A13: EXEMPLE FICTIF – format attendu (à supprimer) | B13: 99 | C13: 30 | D13: 9 | E13: NON | F13: 1 | G13: 0.85 | H13: 4000 | I13: =B13/(1+Paramètres!$B$4) -> 81.818182 | J13: =B13*Paramètres!$B$5+Paramètres!$B$6 -> 1.735 | K13: =IF(E13="OUI",F13*Paramètres!$B$12+Paramètres!$B$13,0) -> 0 | L13: =IF(OR(C13="",D13=""),"à renseigner",I13-C13-D13-J13-K13) -> 41.083182 | M13: =I13-J13-K13-Paramètres!$B$10 -> 40.083182 | N13: =I13-J13-K13-Paramètres!$B$11 -> 45.083182 | O13: =L13 -> 41.083182 | P13: =IF(ISNUMBER(L13),IF(L13>0,Paramètres!$B$7/L13,"marge ≤ 0"),"") -> 4.8681721 | Q13: =IF(ISNUMBER(L13),IF(L13>0,Paramètres!$B$8/L13,"marge ≤ 0"),"") -> 0.015821559 | R13: =IF(ISNUMBER(L13),L13-B13*Paramètres!$B$14,"") -> 36.133182 | S13: =IF(G13="","Enchères à relever",IF(G13>Paramètres!$B$9,"ÉLIMINÉ : enchère > seuil",IF(NOT(ISNUMBER(L13)),"Coûts fournisseur à relever",IF(L13>=Paramètres!$B$10,"OK marge ≥ 40 €",IF(L13>=Paramètres!$B$11,"Limite : marge 35–40 €","ÉLIMINÉ : marge < 35 €"))))) -> OK marge ≥ 40 €
A15: Prix de vente TTC = hypothèses (milieu des fourchettes de ta pré-analyse), à ajuster selon les prix concurrents relevés.
A16: « Achat max » = ce que tu peux payer au fournisseur (produit + livraison) en gardant la marge cible : c'est le chiffre à comparer aux devis fournisseurs.
A17: CPA maximal = marge brute : au-delà, chaque vente obtenue par la pub te coûte plus qu'elle ne rapporte.

Sheet Scénarios
A1: Scénarios sur 1 mois de pub (200 €)
A2: Par défaut : marge = 40 € (ta cible) et CPC moyen = 0,65 € (ton plafond). Remplace par les vrais chiffres dès que tu les as.
A4: Marge brute par vente (€) | B4: =Paramètres!$B$10 -> 40 | C4: Lien Paramètres (cible). Remplace par la marge réelle de l'onglet Rentabilité.
A5: CPC moyen réellement payé (€) | B5: =Paramètres!$B$8 -> 0.65 | C5: Lien Paramètres (plafond). Le CPC réel est souvent plus bas que le plafond.
A6: Prix de vente TTC (€) | B6: 99 | C6: Hypothèse.
A7: Budget du mois (€) | B7: =Paramètres!$B$7 -> 200 | C7: Lien Paramètres.
A8: Taux de conversion d'équilibre | B8: =IF(B4>0,B5/B4,0) -> 0.01625 | C8: Calcul : CPC ÷ marge. En dessous, la pub perd de l'argent.
A10: Indicateur | B10: Pessimiste | C10: Médian | D10: Optimiste
A11: Taux de conversion (visites → commande) | B11: 0.01 | C11: 0.015 | D11: 0.025
A12: Clics achetés dans le mois | B12: =IF($B$5>0,$B$7/$B$5,0) -> 307.69231 | C12: =IF($B$5>0,$B$7/$B$5,0) -> 307.69231 | D12: =IF($B$5>0,$B$7/$B$5,0) -> 307.69231
A13: Ventes attendues | B13: =B12*B11 -> 3.0769231 | C13: =C12*C11 -> 4.6153846 | D13: =D12*D11 -> 7.6923077
A14: Chiffre d'affaires TTC (€) | B14: =B13*$B$6 -> 304.61538 | C14: =C13*$B$6 -> 456.92308 | D14: =D13*$B$6 -> 761.53846
A15: Marge brute totale (€) | B15: =B13*$B$4 -> 123.07692 | C15: =C13*$B$4 -> 184.61538 | D15: =D13*$B$4 -> 307.69231
A16: Résultat après pub (€) | B16: =B15-$B$7 -> -76.923077 | C16: =C15-$B$7 -> -15.384615 | D16: =D15-$B$7 -> 107.69231
A17: Résultat après pub et frais fixes (€) | B17: =B16-Paramètres!$B$15-Paramètres!$B$16 -> -142.92308 | C17: =C16-Paramètres!$B$15-Paramètres!$B$16 -> -81.384615 | D17: =D16-Paramètres!$B$15-Paramètres!$B$16 -> 41.692308
A18: Coût par vente – CPA (€) | B18: =IF(B13>0,$B$7/B13,"") -> 65 | C18: =IF(C13>0,$B$7/C13,"") -> 43.333333 | D18: =IF(D13>0,$B$7/D13,"") -> 26
A19: ROAS (CA TTC ÷ pub) | B19: =IF($B$7>0,B14/$B$7,0) -> 1.5230769 | C19: =IF($B$7>0,C14/$B$7,0) -> 2.2846154 | D19: =IF($B$7>0,D14/$B$7,0) -> 3.8076923
A20: Clics nécessaires pour 1 vente en moyenne | B20: =IF(B11>0,1/B11,"") -> 100 | C20: =IF(C11>0,1/C11,"") -> 66.666667 | D20: =IF(D11>0,1/D11,"") -> 40
A21: Probabilité de 0 vente sur 100 clics | B21: =(1-B11)^100 -> 0.36603234 | C21: =(1-C11)^100 -> 0.22060891 | D21: =(1-D11)^100 -> 0.07951729
A23: Ligne 21 : même un bon produit peut faire 0 vente sur 100 clics par malchance. La règle d'arrêt à 100 clics est un compromis budget / certitude.
A25: Sensibilité : résultat après pub (€) selon CPC moyen et taux de conversion, marge = cellule B4
A26: CPC moyen ↓ / Conversion → | B26: 0.01 | C26: 0.015 | D26: 0.02 | E26: 0.025 | F26: 0.03
A27: 0.36 | B27: =IF($A27>0,$B$7/$A27*B$26*$B$4-$B$7,0) -> 22.222222 | C27: =IF($A27>0,$B$7/$A27*C$26*$B$4-$B$7,0) -> 133.33333 | D27: =IF($A27>0,$B$7/$A27*D$26*$B$4-$B$7,0) -> 244.44444 | E27: =IF($A27>0,$B$7/$A27*E$26*$B$4-$B$7,0) -> 355.55556 | F27: =IF($A27>0,$B$7/$A27*F$26*$B$4-$B$7,0) -> 466.66667
A28: 0.5 | B28: =IF($A28>0,$B$7/$A28*B$26*$B$4-$B$7,0) -> -40 | C28: =IF($A28>0,$B$7/$A28*C$26*$B$4-$B$7,0) -> 40 | D28: =IF($A28>0,$B$7/$A28*D$26*$B$4-$B$7,0) -> 120 | E28: =IF($A28>0,$B$7/$A28*E$26*$B$4-$B$7,0) -> 200 | F28: =IF($A28>0,$B$7/$A28*F$26*$B$4-$B$7,0) -> 280
A29: 0.65 | B29: =IF($A29>0,$B$7/$A29*B$26*$B$4-$B$7,0) -> -76.923077 | C29: =IF($A29>0,$B$7/$A29*C$26*$B$4-$B$7,0) -> -15.384615 | D29: =IF($A29>0,$B$7/$A29*D$26*$B$4-$B$7,0) -> 46.153846 | E29: =IF($A29>0,$B$7/$A29*E$26*$B$4-$B$7,0) -> 107.69231 | F29: =IF($A29>0,$B$7/$A29*F$26*$B$4-$B$7,0) -> 169.23077
A30: 0.8 | B30: =IF($A30>0,$B$7/$A30*B$26*$B$4-$B$7,0) -> -100 | C30: =IF($A30>0,$B$7/$A30*C$26*$B$4-$B$7,0) -> -50 | D30: =IF($A30>0,$B$7/$A30*D$26*$B$4-$B$7,0) -> 0 | E30: =IF($A30>0,$B$7/$A30*E$26*$B$4-$B$7,0) -> 50 | F30: =IF($A30>0,$B$7/$A30*F$26*$B$4-$B$7,0) -> 100
A31: 1 | B31: =IF($A31>0,$B$7/$A31*B$26*$B$4-$B$7,0) -> -120 | C31: =IF($A31>0,$B$7/$A31*C$26*$B$4-$B$7,0) -> -80 | D31: =IF($A31>0,$B$7/$A31*D$26*$B$4-$B$7,0) -> -40 | E31: =IF($A31>0,$B$7/$A31*E$26*$B$4-$B$7,0) -> 0 | F31: =IF($A31>0,$B$7/$A31*F$26*$B$4-$B$7,0) -> 40
A32: 1.2 | B32: =IF($A32>0,$B$7/$A32*B$26*$B$4-$B$7,0) -> -133.33333 | C32: =IF($A32>0,$B$7/$A32*C$26*$B$4-$B$7,0) -> -100 | D32: =IF($A32>0,$B$7/$A32*D$26*$B$4-$B$7,0) -> -66.666667 | E32: =IF($A32>0,$B$7/$A32*E$26*$B$4-$B$7,0) -> -33.333333 | F32: =IF($A32>0,$B$7/$A32*F$26*$B$4-$B$7,0) -> 0
A34: 0,36 € = CPC médian Shopping Europe toutes catégories (smarter-ecommerce.com, 12/10/2026) : repère, pas une donnée de ta niche.

Sheet Concurrence relevée
A1: Prix concurrents relevés (zooplus.fr, recherche interne, 12/10/2026)
A2: Prix affiché sur la liste de résultats = souvent la PLUS PETITE taille du produit. Vérifier la taille L/XL sur la fiche avant conclusion. Google Shopping, Amazon, Decathlon : non consultables depuis cet environnement (blocage).
A4: Niche | B4: Enseigne | C4: Produit | D4: Prix affiché (€) | E4: Nb d'avis | F4: < 60 € ? | G4: Requête
A5: Lit orthopédique chien | B5: Zooplus | C5: Canapé orthopédique gris pour chien | D5: 31.49 | E5: 2640 | F5: =IF(D5<60,"OUI","non") -> OUI | G5: lit orthopédique
A6: Lit orthopédique chien | B6: Zooplus | C6: Coussin orthopédique Pawz & Pepper Colorado | D6: 42.99 | E6: 95 | F6: =IF(D6<60,"OUI","non") -> OUI | G6: lit orthopédique
A7: Lit orthopédique chien | B7: Zooplus | C7: Matelas à mémoire de forme TIAKI | D7: 50.99 | E7: 33 | F7: =IF(D7<60,"OUI","non") -> OUI | G7: lit orthopédique
A8: Lit orthopédique chien | B8: Zooplus | C8: Panier ovale Memory, gris | D8: 57.49 | E8: 410 | F8: =IF(D8<60,"OUI","non") -> OUI | G8: lit orthopédique
A9: Lit orthopédique chien | B9: Zooplus | C9: Petlando LikeOrtho Luke | D9: 59.49 | E9: 0 | F9: =IF(D9<60,"OUI","non") -> OUI | G9: lit orthopédique
A10: Lit orthopédique chien | B10: Zooplus | C10: Coussin Memory, gris | D10: 74.49 | E10: 182 | F10: =IF(D10<60,"OUI","non") -> non | G10: lit orthopédique
A11: Lit orthopédique chien | B11: Zooplus | C11: Ferplast Memor-One | D11: 105.99 | E11: 10 | F11: =IF(D11<60,"OUI","non") -> non | G11: lit orthopédique
A12: Lit orthopédique chien | B12: Zooplus | C12: Panier ovale Memory, gris (grande taille) | D12: 144.99 | E12: 410 | F12: =IF(D12<60,"OUI","non") -> non | G12: lit orthopédique
A13: Rampe / escalier chien | B13: Zooplus | C13: zooplus Basics Escalier Stepway | D13: 17.19 | E13: 112 | F13: =IF(D13<60,"OUI","non") -> OUI | G13: rampe chien
A14: Rampe / escalier chien | B14: Zooplus | C14: Rampe TIAKI Up&Down | D14: 34.49 | E14: 79 | F14: =IF(D14<60,"OUI","non") -> OUI | G14: rampe chien
A15: Rampe / escalier chien | B15: Zooplus | C15: Rampe Backstage pour chien | D15: 52.99 | E15: 28 | F15: =IF(D15<60,"OUI","non") -> OUI | G15: rampe chien
A16: Rampe / escalier chien | B16: Zooplus | C16: Trixie Rampe pliante, noir | D16: 60.99 | E16: 1 | F16: =IF(D16<60,"OUI","non") -> non | G16: rampe chien
... A21: Arbre à chat XXL | B21: Zooplus | C21: Arbre à chat Atlas | D21: 121.99 | E21: 2514 | F21: =IF(D21<60,"OUI","non") -> non | G21: arbre à chat xxl

Sheet Sources
A1: Sources (consultées le 12/10/2026)
A3: Donnée | B3: URL | C3: Remarque
A4: Prix Zooplus | B4: https://www.zooplus.fr/search/results?q=lit%20orthop%C3%A9dique (idem « rampe chien », « arbre à chat xxl ») | C4: Relevé direct
A5: CPC médian Shopping Europe 0,36 € | B5: https://smarter-ecommerce.com/en/smec-market-observer/metrics/cpc | C5: Page mise à jour le 12/10/2026, toutes catégories, pas de détail France
A6: Taux de conversion Shopping 3,03 % (marché, en baisse de 30 % sur un an) | B6: https://smarter-ecommerce.com/en/smec-market-observer/monthly-market-pulse/july-2026 | C6: Via recherche web ; annonceurs établis, pas une boutique neuve
A7: Droit de douane 3 € / catégorie (01/07/2026–01/07/2028) | B7: https://www.info.gouv.fr/actualite/taxe-sur-les-petits-colis-ce-qui-change | C7: Officiel FR
A8: Redevance UE 2 € / article au 01/11/2026 | B8: https://nshift.com/blog/eu-customs-changes-ecommerce-2026 ; https://www.cleolabs.co/en/blog/eu-customs-second-parcel-fee-2026 | C8: Sources divergentes : montant non confirmé officiellement
A9: Shopify Payments FR 1,5 % + 0,25 € | B9: https://getkanal.com/fr/blog/shopify-payments-frais | C9: Cite la page tarifs Shopify FR du 07/10/2026
A10: Shopify Basic 36 €/mois | B10: https://speed-ecom.eu/shopify-quel-forfait-choisir-pour-son-site-e-commerce/ | C10: Vérifié par la source le 26/08/2026
A11: dropshippingXL ≈ 30 €/mois | B11: https://ecommerce-platforms.com/fr/articles/dropshippingxl-by-vidaxl-review | C11: Avis tiers, non vérifié
